mseep_arxiv_latex_mcp-0.1.6.dist-info/licenses/LICENSE
server/main.py
mseep_arxiv_latex_mcp-0.1.6.dist-info/METADATA
mseep_arxiv_latex_mcp-0.1.6.dist-info/WHEEL
mseep_arxiv_latex_mcp-0.1.6.dist-info/top_level.txt
mseep_arxiv_latex_mcp-0.1.6.dist-info/RECORD
